Metadata-Version: 1.0
Name: logger
Version: 1.1
Summary: Python logging helper
Home-page: UNKNOWN
Author: Pavel Paulau
Author-email: pavel.paulau@gmail.com
License: UNKNOWN
Platform: UNKNOWN
